chat_analyzer/__init__.py
chat_analyzer/__main__.py
chat_analyzer/analyzer.py
chat_analyzer/cli.py
chat_analyzer/dataformat.py
chat_analyzer/metadata.py
chat_analyzer/util.py
chat_analyzer/chat_downloader/__init__.py
chat_analyzer/chat_downloader/__main__.py
chat_analyzer/chat_downloader/chat_downloader.py
chat_analyzer/chat_downloader/cli.py
chat_analyzer/chat_downloader/debugging.py
chat_analyzer/chat_downloader/errors.py
chat_analyzer/chat_downloader/metadata.py
chat_analyzer/chat_downloader/formatting/__init__.py
chat_analyzer/chat_downloader/formatting/custom_formats.json
chat_analyzer/chat_downloader/formatting/format.py
chat_analyzer/chat_downloader/output/__init__.py
chat_analyzer/chat_downloader/output/continuous_write.py
chat_analyzer/chat_downloader/sites/__init__.py
chat_analyzer/chat_downloader/sites/common.py
chat_analyzer/chat_downloader/sites/facebook.py
chat_analyzer/chat_downloader/sites/reddit.py
chat_analyzer/chat_downloader/sites/twitch.py
chat_analyzer/chat_downloader/sites/youtube.py
chat_analyzer/chat_downloader/utils/__init__.py
chat_analyzer/chat_downloader/utils/core.py
chat_analyzer/chat_downloader/utils/timed_utils.py
chat_analyzer-1.0.6b3.dist-info/LICENSE.txt
chat_analyzer-1.0.6b3.dist-info/METADATA
chat_analyzer-1.0.6b3.dist-info/WHEEL
chat_analyzer-1.0.6b3.dist-info/entry_points.txt
chat_analyzer-1.0.6b3.dist-info/top_level.txt
chat_analyzer-1.0.6b3.dist-info/RECORD
