Metadata-Version: 2.1
Name: chat-analyzer
Version: 1.0.6b3
Summary: A tool used to process and analyze chat data from past live streams, providing summarized information about chat activity over the stream's lifetime.
Home-page: https://github.com/David-Fryd/chat-analyzer
Author: David Fryd
Author-email: info@chatanalyze.com
License: MIT
Project-URL: Website, https://chatanalyze.com
Project-URL: Source, https://github.com/David-Fryd/chat-analyzer
Keywords: chat analytics analyze message twitch youtube streamer video VOD editor
Classifier: Development Status :: 4 - Beta
Classifier: Intended Audience :: End Users/Desktop
Classifier: Intended Audience :: Other Audience
Classifier: Intended Audience :: Developers
Classifier: Intended Audience :: Science/Research
Classifier: Topic :: Communications
Classifier: Topic :: Communications :: Chat
Classifier: License :: OSI Approved :: MIT License
Classifier: Programming Language :: Python :: 3
Classifier: Programming Language :: Python :: 3.7
Classifier: Programming Language :: Python :: 3.8
Classifier: Programming Language :: Python :: 3.9
Requires-Python: >=3
License-File: LICENSE.txt
Requires-Dist: argparse
Requires-Dist: numpy
Requires-Dist: requests
Requires-Dist: isodate
Requires-Dist: docstring-parser
Requires-Dist: colorlog
Requires-Dist: websocket-client
Provides-Extra: dev
Requires-Dist: flake8 ; extra == 'dev'
Requires-Dist: twine ; extra == 'dev'
Requires-Dist: wheel ; extra == 'dev'
Requires-Dist: tox ; extra == 'dev'
Requires-Dist: pytest ; extra == 'dev'
Requires-Dist: coverage ; extra == 'dev'
Requires-Dist: sphinx ; extra == 'dev'
Requires-Dist: sphinx-rtd-theme ; extra == 'dev'
Requires-Dist: sphinxcontrib-programoutput ; extra == 'dev'
